{
  "data": {
    "organization": {
      "pipelines": {
        "edges": [
          {
            "node": {
              "name": "list-service-karate-api",
              "metrics": {
                "edges": [
                  {
                    "node": {
                      "label": "Speed",
                      "value": "58s"
                    }
                  },
                  {
                    "node": {
                      "label": "Reliability",
                      "value": "100%"
                    }
                  },
                  {
                    "node": {
                      "label": "Builds",
                      "value": "1/week"
                    }
                  }
                ]
              },
              "builds": {
                "edges": [
                  {
                    "node": {
                      "id": "QnVpbGQtLS0xZjRmODhiOS1iZWYwLTQ0MjctYTVkNC00OThjMzRkZTU3MTk=",
                      "uuid": "1f4f88b9-bef0-4427-a5d4-498c34de5719",
                      "number": 4,
                      "url": "https://buildkite.com/wayfair/list-service-karate-api/builds/4",
                      "state": "PASSED"
                    }
                  }
                ]
              }
            },
            "cursor": "ktkhMjAyMC0wNi0yNSAxOTo1NjozNC45ODgwNDkwMDAgVVRD2SQ1MTAwZGNlNC1iMDgyLTQzNDctODU0My1kOGU5MWE4ODkxM2E="
          },
          {
            "node": {
              "name": "python-platforms-docker-cuda",
              "metrics": {
                "edges": [
                  {
                    "node": {
                      "label": "Speed",
                      "value": "10s"
                    }
                  },
                  {
                    "node": {
                      "label": "Reliability",
                      "value": "100%"
                    }
                  },
                  {
                    "node": {
                      "label": "Builds",
                      "value": "2/week"
                    }
                  }
                ]
              },
              "builds": {
                "edges": [
                  {
                    "node": {
                      "id": "QnVpbGQtLS1kYjk3YmI1Yy03YTBmLTQ1YjItYTlmYi0wMTlhODU4YmEzZTc=",
                      "uuid": "db97bb5c-7a0f-45b2-a9fb-019a858ba3e7",
                      "number": 2,
                      "url": "https://buildkite.com/wayfair/python-platforms-docker-cuda/builds/2",
                      "state": "PASSED"
                    }
                  },
                  {
                    "node": {
                      "id": "QnVpbGQtLS0wZDhjZDg3Ny0xNzY3LTQ0ZWQtYmM1MS0wY2JkMjM4MGI3ZmQ=",
                      "uuid": "0d8cd877-1767-44ed-bc51-0cbd2380b7fd",
                      "number": 1,
                      "url": "https://buildkite.com/wayfair/python-platforms-docker-cuda/builds/1",
                      "state": "PASSED"
                    }
                  }
                ]
              }
            },
            "cursor": "ktkhMjAyMC0wNi0yNSAxNjo1OTozOS42ODI0NTcwMDAgVVRD2SRiZTNlZDQ3NS01MjJjLTQwZDQtOWE0YS1iNzA1NGI3YzU4NjY="
          },
          {
            "node": {
              "name": "ds-service",
              "metrics": {
                "edges": [
                  {
                    "node": {
                      "label": "Speed",
                      "value": "3.4m"
                    }
                  },
                  {
                    "node": {
                      "label": "Reliability",
                      "value": "100%"
                    }
                  },
                  {
                    "node": {
                      "label": "Builds",
                      "value": "2/week"
                    }
                  }
                ]
              },
              "builds": {
                "edges": [
                  {
                    "node": {
                      "id": "QnVpbGQtLS0wM2RjNWNiYS04NThhLTRmMDktOTUxZS03OWE3MDk1NGI1OTk=",
                      "uuid": "03dc5cba-858a-4f09-951e-79a70954b599",
                      "number": 2,
                      "url": "https://buildkite.com/wayfair/ds-service/builds/2",
                      "state": "PASSED"
                    }
                  },
                  {
                    "node": {
                      "id": "QnVpbGQtLS00Y2Y2Njk5My02MWU0LTRiZTktYTQ4ZC0wZjZmNDBkZDNiYWQ=",
                      "uuid": "4cf66993-61e4-4be9-a48d-0f6f40dd3bad",
                      "number": 1,
                      "url": "https://buildkite.com/wayfair/ds-service/builds/1",
                      "state": "PASSED"
                    }
                  }
                ]
              }
            },
            "cursor": "ktkhMjAyMC0wNi0yNSAxNTo1OToyNi4yMzc3MDIwMDAgVVRD2SRhYjkyZjZkOC0zNDc4LTQ0NmItYTMyMy0zMGI3ZmNkMDlkZTY="
          },
          {
            "node": {
              "name": "SUOP Monolith pipeline - Customer Incident Dashboard Frontend",
              "metrics": {
                "edges": [
                  {
                    "node": {
                      "label": "Speed",
                      "value": "9.3m"
                    }
                  },
                  {
                    "node": {
                      "label": "Reliability",
                      "value": "100%"
                    }
                  },
                  {
                    "node": {
                      "label": "Builds",
                      "value": "1/week"
                    }
                  }
                ]
              },
              "builds": {
                "edges": [
                  {
                    "node": {
                      "id": "QnVpbGQtLS0zNGYwYWY2NC0xZDViLTQ1NzgtOWJlMC1lM2E1YTY0NWVmYmE=",
                      "uuid": "34f0af64-1d5b-4578-9be0-e3a5a645efba",
                      "number": 1,
                      "url": "https://buildkite.com/wayfair/suop-monolith-pipeline-customer-incident-dashboard-frontend/builds/1",
                      "state": "PASSED"
                    }
                  }
                ]
              }
            },
            "cursor": "ktkhMjAyMC0wNi0yNSAxNDo0NDo1Mi41MDgxNjgwMDAgVVRD2SQwOTg0YzY4Ny00NzAzLTQ4ZTQtYWEwYi1mNDdjNjk0MDM1NDQ="
          },
          {
            "node": {
              "name": "SUOP Monolith pipeline - Lead Time Performance Frontend",
              "metrics": {
                "edges": [
                  {
                    "node": {
                      "label": "Speed",
                      "value": "8.4m"
                    }
                  },
                  {
                    "node": {
                      "label": "Reliability",
                      "value": "83%"
                    }
                  },
                  {
                    "node": {
                      "label": "Builds",
                      "value": "6/week"
                    }
                  }
                ]
              },
              "builds": {
                "edges": [
                  {
                    "node": {
                      "id": "QnVpbGQtLS03OTM1MTM1ZC1hOWQzLTRlMDMtYTNiZC1iNmU3NjVmYTM3NDU=",
                      "uuid": "7935135d-a9d3-4e03-a3bd-b6e765fa3745",
                      "number": 6,
                      "url": "https://buildkite.com/wayfair/suop-monolith-pipeline-lead-time-performance-frontend/builds/6",
                      "state": "PASSED"
                    }
                  },
                  {
                    "node": {
                      "id": "QnVpbGQtLS1lYmNlZjc5Ni1kODBhLTQyZDItYTg5NC1jNDRmNmNmNDM4MmY=",
                      "uuid": "ebcef796-d80a-42d2-a894-c44f6cf4382f",
                      "number": 5,
                      "url": "https://buildkite.com/wayfair/suop-monolith-pipeline-lead-time-performance-frontend/builds/5",
                      "state": "PASSED"
                    }
                  },
                  {
                    "node": {
                      "id": "QnVpbGQtLS0wZDE5ZDljMi1jMmNkLTQ3NTUtYjA5ZS05ZTI2NjVkOTM5NmE=",
                      "uuid": "0d19d9c2-c2cd-4755-b09e-9e2665d9396a",
                      "number": 4,
                      "url": "https://buildkite.com/wayfair/suop-monolith-pipeline-lead-time-performance-frontend/builds/4",
                      "state": "PASSED"
                    }
                  },
                  {
                    "node": {
                      "id": "QnVpbGQtLS00MzgwYzJhZi00ZTdjLTQ0MTEtYjI4NC1hNDk2NDU0Y2Q1MmI=",
                      "uuid": "4380c2af-4e7c-4411-b284-a496454cd52b",
                      "number": 3,
                      "url": "https://buildkite.com/wayfair/suop-monolith-pipeline-lead-time-performance-frontend/builds/3",
                      "state": "PASSED"
                    }
                  },
                  {
                    "node": {
                      "id": "QnVpbGQtLS00ZmU3MTAwYy02MTkyLTQxMDYtODZjNS04YzJkYmMxZTc5Njc=",
                      "uuid": "4fe7100c-6192-4106-86c5-8c2dbc1e7967",
                      "number": 2,
                      "url": "https://buildkite.com/wayfair/suop-monolith-pipeline-lead-time-performance-frontend/builds/2",
                      "state": "PASSED"
                    }
                  },
                  {
                    "node": {
                      "id": "QnVpbGQtLS04YjAyMWNjMi03Yzk3LTQxNmUtOTBjZi1lODkyNzgxNTg2MGY=",
                      "uuid": "8b021cc2-7c97-416e-90cf-e8927815860f",
                      "number": 1,
                      "url": "https://buildkite.com/wayfair/suop-monolith-pipeline-lead-time-performance-frontend/builds/1",
                      "state": "FAILED"
                    }
                  }
                ]
              }
            },
            "cursor": "ktkhMjAyMC0wNi0yNSAxMTozMTo0MS41OTg4NzMwMDAgVVRD2SQ0ZDczODg3Mi1kM2M4LTRjMmItOGVjNy0wODFlNjRjMjE1YTI="
          },
          {
            "node": {
              "name": "analytics-kronos-compiler",
              "metrics": {
                "edges": [
                  {
                    "node": {
                      "label": "Speed",
                      "value": "4.6m"
                    }
                  },
                  {
                    "node": {
                      "label": "Reliability",
                      "value": "100%"
                    }
                  },
                  {
                    "node": {
                      "label": "Builds",
                      "value": "2/week"
                    }
                  }
                ]
              },
              "builds": {
                "edges": [
                  {
                    "node": {
                      "id": "QnVpbGQtLS1lOWZkYzU3NS1kMDMxLTQyNmUtOWEyYS00ZTMzOTJiMTU4ZTk=",
                      "uuid": "e9fdc575-d031-426e-9a2a-4e3392b158e9",
                      "number": 2,
                      "url": "https://buildkite.com/wayfair/analytics-kronos-compiler/builds/2",
                      "state": "PASSED"
                    }
                  },
                  {
                    "node": {
                      "id": "QnVpbGQtLS0zZjY3OTNhZi01YjU1LTQ1OWUtOWIxYi0yMGRiMmIwNzQxNTI=",
                      "uuid": "3f6793af-5b55-459e-9b1b-20db2b074152",
                      "number": 1,
                      "url": "https://buildkite.com/wayfair/analytics-kronos-compiler/builds/1",
                      "state": "PASSED"
                    }
                  }
                ]
              }
            },
            "cursor": "ktkhMjAyMC0wNi0yNSAwMTo0ODoxNC42Mjc5MzQwMDAgVVRD2SRmYzk3ZTgwYi1iNWViLTRlODYtYTg0Yi02ZjA1YTM5ZDZiNTI="
          },
          {
            "node": {
              "name": "bde-atwood-api",
              "metrics": {
                "edges": [
                  {
                    "node": {
                      "label": "Speed",
                      "value": "3.3m"
                    }
                  },
                  {
                    "node": {
                      "label": "Reliability",
                      "value": "0%"
                    }
                  },
                  {
                    "node": {
                      "label": "Builds",
                      "value": "2/week"
                    }
                  }
                ]
              },
              "builds": {
                "edges": [
                  {
                    "node": {
                      "id": "QnVpbGQtLS1lMzAyYjMxZS0zNmUxLTQ5NmItYTk4My1lMzEyZWNlNWE2MmM=",
                      "uuid": "e302b31e-36e1-496b-a983-e312ece5a62c",
                      "number": 5,
                      "url": "https://buildkite.com/wayfair/bde-atwood-api/builds/5",
                      "state": "FAILED"
                    }
                  },
                  {
                    "node": {
                      "id": "QnVpbGQtLS0zM2MyMWU0My00NGNkLTRkMjUtYjVkNy0wM2IyMDQwZWIxM2I=",
                      "uuid": "33c21e43-44cd-4d25-b5d7-03b2040eb13b",
                      "number": 3,
                      "url": "https://buildkite.com/wayfair/bde-atwood-api/builds/3",
                      "state": "FAILED"
                    }
                  }
                ]
              }
            },
            "cursor": "ktkhMjAyMC0wNi0yNCAyMDoxMzo1NC4zOTI4NTQwMDAgVVRD2SRiMzM1Yjk1Ni02ZGZjLTQzNDAtYTQyNC0zZjllOGNiM2RmNzU="
          },
          {
            "node": {
              "name": "Sergey - wayfair-android stores apps release branch to Firebase App Distribution",
              "metrics": {
                "edges": [
                  {
                    "node": {
                      "label": "Speed",
                      "value": null
                    }
                  },
                  {
                    "node": {
                      "label": "Reliability",
                      "value": "0%"
                    }
                  },
                  {
                    "node": {
                      "label": "Builds",
                      "value": "1/week"
                    }
                  }
                ]
              },
              "builds": {
                "edges": [
                  {
                    "node": {
                      "id": "QnVpbGQtLS00ZGYzNWY2MC05YTY3LTQ1MGQtYTA3OC1hYjQ1MDE2Y2M1YWM=",
                      "uuid": "4df35f60-9a67-450d-a078-ab45016cc5ac",
                      "number": 1,
                      "url": "https://buildkite.com/wayfair/sergey-wayfair-android-stores-apps-release-branch-to-firebase-app-distribution/builds/1",
                      "state": "CANCELED"
                    }
                  }
                ]
              }
            },
            "cursor": "ktkhMjAyMC0wNi0yNCAxODozNzozOC40NjM2NTMwMDAgVVRD2SQxY2E1Mjk4ZS1jMTlhLTRlNTQtYTUzZS0zMDdjM2E4YTQ2Yjc="
          },
          {
            "node": {
              "name": "rundeck-processor",
              "metrics": {
                "edges": [
                  {
                    "node": {
                      "label": "Speed",
                      "value": "9.7m"
                    }
                  },
                  {
                    "node": {
                      "label": "Reliability",
                      "value": "100%"
                    }
                  },
                  {
                    "node": {
                      "label": "Builds",
                      "value": "4/week"
                    }
                  }
                ]
              },
              "builds": {
                "edges": [
                  {
                    "node": {
                      "id": "QnVpbGQtLS1hZTNkNjRiMS1iN2NiLTQyZWMtYjMzOS0wNDExODFkMTYzZDQ=",
                      "uuid": "ae3d64b1-b7cb-42ec-b339-041181d163d4",
                      "number": 5,
                      "url": "https://buildkite.com/wayfair/rundeck-processor/builds/5",
                      "state": "PASSED"
                    }
                  },
                  {
                    "node": {
                      "id": "QnVpbGQtLS01NjY1MzViZi1iNmM4LTRkNWUtYTMwMC1jNTAwN2YxMzc0NWM=",
                      "uuid": "566535bf-b6c8-4d5e-a300-c5007f13745c",
                      "number": 3,
                      "url": "https://buildkite.com/wayfair/rundeck-processor/builds/3",
                      "state": "PASSED"
                    }
                  },
                  {
                    "node": {
                      "id": "QnVpbGQtLS1hNTgxMGNiMy04NjYyLTQxMzAtODE2Zi0wMGMyZmJjY2M3NjE=",
                      "uuid": "a5810cb3-8662-4130-816f-00c2fbccc761",
                      "number": 2,
                      "url": "https://buildkite.com/wayfair/rundeck-processor/builds/2",
                      "state": "PASSED"
                    }
                  },
                  {
                    "node": {
                      "id": "QnVpbGQtLS00NGUyNjIxYi04ZmJkLTQ1YjctODI0Mi0xNzY1MzY1Y2JmNDA=",
                      "uuid": "44e2621b-8fbd-45b7-8242-1765365cbf40",
                      "number": 1,
                      "url": "https://buildkite.com/wayfair/rundeck-processor/builds/1",
                      "state": "PASSED"
                    }
                  }
                ]
              }
            },
            "cursor": "ktkhMjAyMC0wNi0yNCAxNjo0NjowNS4yODEwNzEwMDAgVVRD2SRiZTMyYjExYi1kY2JkLTQ3ODMtODY2Yi02MjcxZjk0ODJlNGI="
          },
          {
            "node": {
              "name": "Homebase Storybook Deploy Preview",
              "metrics": {
                "edges": [
                  {
                    "node": {
                      "label": "Speed",
                      "value": "2s"
                    }
                  },
                  {
                    "node": {
                      "label": "Reliability",
                      "value": "0%"
                    }
                  },
                  {
                    "node": {
                      "label": "Builds",
                      "value": "1/week"
                    }
                  }
                ]
              },
              "builds": {
                "edges": [
                  {
                    "node": {
                      "id": "QnVpbGQtLS1iZDZjMzI2MC0zZjE1LTQ2ZDMtYjg4MC1lZTg1MDI2Yzk0MDU=",
                      "uuid": "bd6c3260-3f15-46d3-b880-ee85026c9405",
                      "number": 15,
                      "url": "https://buildkite.com/wayfair/homebase-storybook-deploy-preview/builds/15",
                      "state": "FAILED"
                    }
                  }
                ]
              }
            },
            "cursor": "ktkhMjAyMC0wNi0yNCAxNjo0NDo1Mi4xMDczODgwMDAgVVRD2SQxYzgxYzA3ZS1lZjE5LTQ1YmItYjU1My0xMWQ3ODhlZWYyMzQ="
          }
        ],
        "pageInfo": {
          "hasNextPage": true
        }
      }
    }
  }
}
